Metadata-Version: 2.1
Name: nornir-progressbar
Version: 0.1.0
Summary: Multi-threaded runner plugin for nornir that prints a cute progress bar.
Home-page: https://github.com/matman26/nornir_progressbar
Author: Matheus Augusto da Silva
Author-email: a.matheus26@hotmail.com
License: apache-2.0
Download-URL: https://github.com/matman26/nornir_progressbar/archive/refs/tags/v0.1.1.tar.gz
Keywords: nornir,tqdm,runner,plugin
Platform: UNKNOWN
Classifier: Development Status :: 3 - Alpha
Classifier: Intended Audience :: Developers
Classifier: Topic :: Software Development :: Build Tools
Classifier: License :: OSI Approved :: Apache Software License
Classifier: Programming Language :: Python :: 3
Classifier: Programming Language :: Python :: 3.5
Classifier: Programming Language :: Python :: 3.6
Classifier: Programming Language :: Python :: 3.7
Classifier: Programming Language :: Python :: 3.8
Classifier: Programming Language :: Python :: 3.9
Classifier: Programming Language :: Python :: 3.10
License-File: LICENSE
License-File: NOTICE
